[
    {
        "name": "dioxus-std",
        "description": "A library to provide abstractions to access common utilities when developing Dioxus applications.",
        "category": "Util",
        "github": {
            "username": "DioxusLabs",
            "repo": "dioxus-std"
        },
        "link": null
    },
    {
        "name": "dioxus-logger",
        "description": "A logging utility to provide a standard interface whether you're targeting web, desktop, or mobile.",
        "category": "Logging",
        "github": {
            "username": "DogeDark",
            "repo": "dioxus-logger"
        },
        "link": null
    },
    {
        "name": "Geolocation Example",
        "description": "Dioxus & Dioxus-STD geolocation demonstration.",
        "category": "Example",
        "github": {
            "username": "DogeDark",
            "repo": "dioxus-geolocation-example"
        },
        "link": null
    },
    {
        "name": "dioxus-sortable",
        "description": "Sortable tables for Dioxus.",
        "category": "Components",
        "github": {
            "username": "feral-dot-io",
            "repo": "dioxus-sortable"
        },
        "link": null
    },
    {
        "name": "Deploy Dioxus to Vercel",
        "description": "Deploy dioxus-web to Vercel.",
        "category": "Deployment",
        "github": {
            "username": "lucifer1004",
            "repo": "dioxus-vercel-demo"
        },
        "link": null
    },
    {
        "name": "NixOS Install Script",
        "description": "Fetches necessary dependencies for running Dioxus in desktop mode when using the Nix package manager.",
        "category": "Deployment",
        "github": null,
        "link": "https://gist.github.com/FruitieX/73afe3eb15da45e0e05d5c9cf5d318fc"
    },
    {
        "name": "Golde",
        "description": "Use Dioxus to execute JavaScript and get the result.",
        "category": "Util",
        "github": {
            "username": "mrxiaozhuox",
            "repo": "golde"
        },
        "link": null
    },
    {
        "name": "Freya",
        "description": "A skia renderer for Dioxus.",
        "category": "Renderer",
        "github": {
            "username": "marc2332",
            "repo": "freya"
        },
        "link": null
    },
    {
        "name": "Fermi",
        "description": "Global state management build on the concept of atoms.",
        "category": "Util",
        "github": null,
        "link": "https://github.com/DioxusLabs/dioxus/tree/master/packages/fermi"
    },
    {
        "name": "dioxus-websocket-hooks",
        "description": "Dioxus hooks for websocket connections.",
        "category": "Util",
        "github": {
            "username": "FruitieX",
            "repo": "dioxus-websocket-hooks"
        },
        "link": null
    },
    {
        "name": "dioxus-helmet",
        "description": "Place elements in the head tag of your document.",
        "category": "Util",
        "github": {
            "username": "saicu",
            "repo": "dioxus-helmet"
        },
        "link": null
    },
    {
        "name": "dioxus-layout",
        "description": "Layout components for Dioxus.",
        "category": "Components",
        "github": null,
        "link": "https://gitlab.com/MAlrusayni/dioxus-layout"
    },
    {
        "name": "dioxus-free-icons",
        "description": "Free icon components for Dioxus.",
        "category": "Components",
        "github": {
            "username": "nissy-dev",
            "repo": "dioxus-free-icons"
        },
        "link": null
    },
    {
        "name": "dioxus-material-icons",
        "description": "Material icons for Dioxus.",
        "category": "Components",
        "github": {
            "username": "lennartkloock",
            "repo": "dioxus-material-icons"
        },
        "link": null
    },
    {
        "name": "File Navigator Example",
        "description": "Shows how a Dioxus app can directly leverage system calls and libraries.",
        "category": "Example",
        "github": null,
        "link": "https://github.com/DioxusLabs/example-projects/tree/master/file-explorer"
    },
    {
        "name": "Todo-MVC Example",
        "description": "An example of a Todo-MVC built with different patterns.",
        "category": "Example",
        "github": null,
        "link": "https://github.com/DioxusLabs/example-projects/tree/master/todomvc"
    },
    {
        "name": "Ecommerce Example",
        "description": "A liveview app that leverages the FakeStoreAPI and Tailwind.",
        "category": "Example",
        "github": null,
        "link": "https://github.com/DioxusLabs/example-projects/tree/master/ecommerce-site"
    },
    {
        "name": "WIFI Scanner Example",
        "description": "An example of utilizing background-threads in a desktop Dioxus app.",
        "category": "Example",
        "github": null,
        "link": "https://github.com/DioxusLabs/example-projects/tree/master/wifi-scanner"
    }
]